LICENSE
MANIFEST.in
README.md
pyproject.toml
setup.cfg
setup.py
wagtail_fedit/__init__.py
wagtail_fedit/apps.py
wagtail_fedit/errors.py
wagtail_fedit/hooks.py
wagtail_fedit/models.py
wagtail_fedit/settings.py
wagtail_fedit/toolbar.py
wagtail_fedit/urls.py
wagtail_fedit/utils.py
wagtail_fedit.egg-info/PKG-INFO
wagtail_fedit.egg-info/SOURCES.txt
wagtail_fedit.egg-info/dependency_links.txt
wagtail_fedit.egg-info/requires.txt
wagtail_fedit.egg-info/top_level.txt
wagtail_fedit/adapters/__init__.py
wagtail_fedit/adapters/base.py
wagtail_fedit/adapters/block.py
wagtail_fedit/adapters/field.py
wagtail_fedit/adapters/funcs.py
wagtail_fedit/adapters/misc.py
wagtail_fedit/adapters/models.py
wagtail_fedit/adapters/registry.py
wagtail_fedit/forms/__init__.py
wagtail_fedit/forms/blocks.py
wagtail_fedit/forms/fields.py
wagtail_fedit/locale/nl/LC_MESSAGES/django.mo
wagtail_fedit/locale/nl/LC_MESSAGES/django.po
wagtail_fedit/migrations/__init__.py
wagtail_fedit/migrations/__pycache__/__init__.cpython-311.pyc
wagtail_fedit/static/wagtail_fedit/css/frontend.css
wagtail_fedit/static/wagtail_fedit/css/furniture.css
wagtail_fedit/static/wagtail_fedit/css/userbar-menu.css
wagtail_fedit/static/wagtail_fedit/js/edit.js
wagtail_fedit/static/wagtail_fedit/js/licenses/TIPPY.LICENSE
wagtail_fedit/templates/wagtail_fedit/_hook_output.html
wagtail_fedit/templates/wagtail_fedit/content/editable_adapter.html
wagtail_fedit/templates/wagtail_fedit/content/editable_dom_positioned_adapter.html
wagtail_fedit/templates/wagtail_fedit/content/buttons/admin_link.html
wagtail_fedit/templates/wagtail_fedit/content/buttons/edit_adapter.html
wagtail_fedit/templates/wagtail_fedit/editor/action_confirm.html
wagtail_fedit/templates/wagtail_fedit/editor/action_publish_confirm.html
wagtail_fedit/templates/wagtail_fedit/editor/adapter_edit_handler.html
wagtail_fedit/templates/wagtail_fedit/editor/adapter_edit_handler_form.html
wagtail_fedit/templates/wagtail_fedit/editor/adapter_form.html
wagtail_fedit/templates/wagtail_fedit/editor/adapter_form_errors.html
wagtail_fedit/templates/wagtail_fedit/editor/adapter_iframe.html
